dwdhandler/__init__.py
dwdhandler/dow_handler.py
dwdhandler/calculation/__init__.py
dwdhandler/calculation/calc_stats.py
dwdhandler/calculation/geo.py
dwdhandler/calculation/return_period.py
dwdhandler/constants/__init__.py
dwdhandler/constants/constpar.py
dwdhandler/constants/filedata.py
dwdhandler/constants/serverdata.py
dwdhandler/helper/__init__.py
dwdhandler/helper/ftp.py
dwdhandler/helper/hfunctions.py
dwdhandler/helper/postgres.py
dwdhandler/plotting/__init__.py
dwdhandler/plotting/plotconstr.py
dwdhandler-0.2.4.dist-info/LICENSE
dwdhandler-0.2.4.dist-info/METADATA
dwdhandler-0.2.4.dist-info/WHEEL
dwdhandler-0.2.4.dist-info/top_level.txt
dwdhandler-0.2.4.dist-info/RECORD
