Metadata-Version: 2.1
Name: dwdhandler
Version: 0.2.4
Summary: Package to handle data from German Weather Service and some simple plotting routines
Home-page: https://github.com/MrTscha/dwdhandler
Author: Tobias Schad
Author-email: Tobias Schad <tobias.schad@googlemail.com>
Maintainer-email: Tobias Schad <tobias.schad@googlemail.com>
License: GNU GENERAL PUBLIC LICENSE
Project-URL: Repository, https://github.com/MrTscha/dwdhandler
Project-URL: Issues, https://github.com/MrTscha/dwdhandler/issues
Keywords: dwd,German Weather Service,Deutscher Wetterdienst
Requires-Python: >=3.8
License-File: LICENSE
Requires-Dist: numpy
Requires-Dist: pandas
Requires-Dist: seaborn
Requires-Dist: matplotlib
Requires-Dist: folium
Requires-Dist: plotly
Requires-Dist: scipy
Requires-Dist: psycopg2
Requires-Dist: sqlalchemy
Requires-Dist: python-dotenv
Provides-Extra: rasterproc
Requires-Dist: pyproj; extra == "rasterproc"
